bsql/__init__.py
bsql/database.py
bsql/json_encoder.py
bsql/migration.py
bsql/model.py
bsql/record.py
bsql/recordset.py
bsql/sql.py
bsql-0.13.0.dist-info/METADATA
bsql-0.13.0.dist-info/RECORD
bsql-0.13.0.dist-info/WHEEL
bsql-0.13.0.dist-info/top_level.txt
